pystockparameter/__init__.py
pystockparameter/api.py
pystockparameter/data/merged_stock_data.xlsx
pystockparameter-0.1.2.dist-info/METADATA
pystockparameter-0.1.2.dist-info/WHEEL
pystockparameter-0.1.2.dist-info/top_level.txt
pystockparameter-0.1.2.dist-info/RECORD
