Metadata-Version: 2.1
Name: pystockparameter
Version: 0.1.2
Summary: Python package to fetch stock data from a merged Excel file
Home-page: https://github.com/yourusername/pystockparameter
Author: PredictRAM
Author-email: support@predictram.com
Classifier: Programming Language :: Python :: 3
Classifier: License :: OSI Approved :: MIT License
Requires-Dist: pandas
Requires-Dist: openpyxl
